ob_dj_store/apis/__init__.py
ob_dj_store/apis/stores/__init__.py
ob_dj_store/apis/stores/filters.py
ob_dj_store/apis/stores/urls.py
ob_dj_store/apis/stores/views.py
ob_dj_store/apis/stores/rest/serializers/serializers.py
ob_dj_store/apis/stripe/__init__.py
ob_dj_store/apis/stripe/serializers.py
ob_dj_store/apis/stripe/urls.py
ob_dj_store/apis/stripe/views.py
ob_dj_store/apis/tap/__init__.py
ob_dj_store/apis/tap/serializers.py
ob_dj_store/apis/tap/urls.py
ob_dj_store/apis/tap/views.py
ob_dj_store/core/__init__.py
ob_dj_store/core/stores/__init__.py
ob_dj_store/core/stores/admin.py
ob_dj_store/core/stores/admin_inlines.py
ob_dj_store/core/stores/apps.py
ob_dj_store/core/stores/managers.py
ob_dj_store/core/stores/receivers.py
ob_dj_store/core/stores/settings_validation.py
ob_dj_store/core/stores/utils.py
ob_dj_store/core/stores/gateway/__init__.py
ob_dj_store/core/stores/gateway/stripe/__init__.py
ob_dj_store/core/stores/gateway/stripe/admin.py
ob_dj_store/core/stores/gateway/stripe/apps.py
ob_dj_store/core/stores/gateway/stripe/managers.py
ob_dj_store/core/stores/gateway/stripe/models.py
ob_dj_store/core/stores/gateway/stripe/utils.py
ob_dj_store/core/stores/gateway/stripe/migrations/0001_initial.py
ob_dj_store/core/stores/gateway/stripe/migrations/__init__.py
ob_dj_store/core/stores/gateway/tap/__init__.py
ob_dj_store/core/stores/gateway/tap/admin.py
ob_dj_store/core/stores/gateway/tap/apps.py
ob_dj_store/core/stores/gateway/tap/managers.py
ob_dj_store/core/stores/gateway/tap/models.py
ob_dj_store/core/stores/gateway/tap/utils.py
ob_dj_store/core/stores/gateway/tap/migrations/0001_initial.py
ob_dj_store/core/stores/gateway/tap/migrations/0002_auto_20220815_1610.py
ob_dj_store/core/stores/gateway/tap/migrations/0003_auto_20220818_1938.py
ob_dj_store/core/stores/gateway/tap/migrations/0004_tapcustomer.py
ob_dj_store/core/stores/gateway/tap/migrations/0005_alter_tappayment_payment_url.py
ob_dj_store/core/stores/gateway/tap/migrations/0006_alter_tappayment_source.py
ob_dj_store-0.0.24.2.dist-info/METADATA
ob_dj_store-0.0.24.2.dist-info/WHEEL
ob_dj_store-0.0.24.2.dist-info/top_level.txt
ob_dj_store-0.0.24.2.dist-info/RECORD
