Metadata-Version: 2.4
Name: ob-dj-store
Version: 0.0.24.2
Summary: OBytes django application for managing ecommerce stores.
Home-page: https://www.obytes.com/
Author: OBytes
Author-email: hello@obytes.com
License: BSD-3-Clause
Classifier: Environment :: Web Environment
Classifier: Framework :: Django
Classifier: Intended Audience :: Developers
Classifier: License :: OSI Approved :: BSD License
Classifier: Operating System :: OS Independent
Classifier: Programming Language :: Python
Classifier: Programming Language :: Python :: 3
Classifier: Programming Language :: Python :: 3 :: Only
Classifier: Programming Language :: Python :: 3.8
Classifier: Topic :: Internet :: WWW/HTTP
Classifier: Topic :: Internet :: WWW/HTTP :: Dynamic Content
Requires-Python: >=3.8
Requires-Dist: django
Requires-Dist: djangorestframework
Requires-Dist: djangorestframework-gis
Requires-Dist: django-filter
Requires-Dist: django-leaflet
Requires-Dist: django-countries
Dynamic: requires-dist
